conda_envfile/__init__.py
conda_envfile/_version.py
conda_envfile-0.5.2.dist-info/LICENSE
conda_envfile-0.5.2.dist-info/METADATA
conda_envfile-0.5.2.dist-info/WHEEL
conda_envfile-0.5.2.dist-info/entry_points.txt
conda_envfile-0.5.2.dist-info/top_level.txt
conda_envfile-0.5.2.dist-info/RECORD
