Metadata-Version: 2.1
Name: conda_envfile
Version: 0.5.2
Summary: Inspect/combine conda YAML environment files
Author-email: Tom de Geus <tom@geus.me>
Project-URL: Source, https://github.com/tdegeus/conda_envfile
Classifier: License :: OSI Approved :: MIT License
Requires-Python: >=3.11
License-File: LICENSE
Requires-Dist: click
Requires-Dist: Jinja2
Requires-Dist: packaging
Requires-Dist: prettytable
Requires-Dist: pyyaml
